multirun/__init__.py
multirun-0.2.2.dist-info/entry_points.txt
multirun-0.2.2.dist-info/WHEEL
multirun-0.2.2.dist-info/METADATA
multirun-0.2.2.dist-info/RECORD
