Metadata-Version: 2.1
Name: multirun
Version: 0.2.2
Summary: Multirun is a simple wrapper around tmux to allow running and monitoring multiple processes at once
Home-page: https://github.com/rsayers/multirun
Author: Rob Sayers
Author-email: rsayers@robsayers.com
Requires-Python: >=3.9,<4.0
Classifier: Programming Language :: Python :: 3
Classifier: Programming Language :: Python :: 3.10
Classifier: Programming Language :: Python :: 3.9
Requires-Dist: toml (>=0.10.2,<0.11.0)
